README.md
pyproject.toml
setup.py
linux/__init__.py
python_linux.egg-info/PKG-INFO
python_linux.egg-info/SOURCES.txt
python_linux.egg-info/dependency_links.txt
python_linux.egg-info/requires.txt
python_linux.egg-info/top_level.txt